CHANGES
LICENSE
MANIFEST.in
README.md
setup.cfg
setup.py
owllib/__init__.py
owllib/entities.py
owllib/ontology.py
owllib/test.py
owllib.egg-info/PKG-INFO
owllib.egg-info/SOURCES.txt
owllib.egg-info/dependency_links.txt
owllib.egg-info/requires.txt
owllib.egg-info/top_level.txt